user_mixins/__init__.py
user_mixins/admin.py
user_mixins/admin_forms.py
user_mixins/backends.py
user_mixins/mixins.py
user_mixins/notifications.py
user_mixins/templates/user_mixins/account_validation_email.html
user_mixins/templates/user_mixins/account_validation_email.txt
user_mixins/templates/user_mixins/password_reset_email.html
user_mixins/templates/user_mixins/password_reset_email.txt
user_mixins/tests/__init__.py
user_mixins/tests/factories.py
user_mixins/tests/models.py
user_mixins/tests/notifications.py
user_mixins/tests/run.py
user_mixins/tests/test_admin.py
user_mixins/tests/test_admin_forms.py
user_mixins/tests/test_backends.py
user_mixins/tests/test_models.py
user_mixins/tests/utils.py
django_user_mixins-0.0.1.dist-info/LICENSE
django_user_mixins-0.0.1.dist-info/METADATA
django_user_mixins-0.0.1.dist-info/WHEEL
django_user_mixins-0.0.1.dist-info/top_level.txt
django_user_mixins-0.0.1.dist-info/RECORD
