Metadata-Version: 2.1
Name: django-user-mixins
Version: 0.0.1
Summary: User model mixins.
Home-page: https://github.com/incuna/django-user-mixins/
Author: Incuna
Author-email: admin@incuna.com
License: BSD
Keywords: django user mixin
Platform: UNKNOWN
Classifier: Development Status :: 5 - Production/Stable
Classifier: Environment :: Web Environment
Classifier: Framework :: Django
Classifier: Intended Audience :: Developers
Classifier: License :: OSI Approved :: BSD License
Classifier: Programming Language :: Python :: 3
Classifier: Programming Language :: Python :: 3.6
Classifier: Programming Language :: Python :: 3.7
Classifier: Programming Language :: Python :: 3.8
Classifier: Topic :: Software Development
Classifier: Topic :: Utilities
Requires-Dist: incuna-mail (<4.2.0,>=4.1.0)
Requires-Dist: incuna-pigeon (<1.0.0,>=0.1.0)
Provides-Extra: avatar
Requires-Dist: django-imagekit (>=3.2) ; extra == 'avatar'
